palm/__init__.py
palm/cli.py
palm/code_generator.py
palm/containerizer.py
palm/environment.py
palm/palm_config.py
palm/palm_exceptions.py
palm/plugin_manager.py
palm/project_setup_utils.py
palm/utils.py
palm/plugins/__init__.py
palm/plugins/base.py
palm/plugins/base_plugin_config.py
palm/plugins/core/__init__.py
palm/plugins/core/core_plugin.py
palm/plugins/core/create_files.py
palm/plugins/core/commands/__init__.py
palm/plugins/core/commands/cmd_build.py
palm/plugins/core/commands/cmd_containerize.py
palm/plugins/core/commands/cmd_init.py
palm/plugins/core/commands/cmd_lint.py
palm/plugins/core/commands/cmd_override.py
palm/plugins/core/commands/cmd_plugin.py
palm/plugins/core/commands/cmd_scaffold.py
palm/plugins/core/commands/cmd_shell.py
palm/plugins/core/commands/cmd_test.py
palm/plugins/core/commands/cmd_update.py
palm/plugins/core/templates/command/new_cmd.tpl.py
palm/plugins/core/templates/command/template-config.yaml
palm/plugins/core/templates/command_group/new_cmd_group.tpl.py
palm/plugins/core/templates/command_group/template-config.yaml
palm/plugins/core/templates/containerize/Dockerfile.txt
palm/plugins/core/templates/containerize/docker-compose.yaml
palm/plugins/core/templates/containerize/entrypoint.sh.txt
palm/plugins/core/templates/containerize/template-config.yaml
palm/plugins/core/templates/plugin/empty_file.py
palm/plugins/core/templates/plugin/plugin_init.tpl.py
palm/plugins/core/templates/plugin/plugin_template.tpl.py
palm/plugins/core/templates/plugin/setup.tpl.py
palm/plugins/core/templates/plugin/template-config.yaml
palm/plugins/repo/__init__.py
palm/plugins/repo/repo_plugin.py
palm/plugins/setup/__init__.py
palm/plugins/setup/setup_plugin.py
palm/plugins/setup/commands/cmd_new.py
palm/plugins/test_internal/__init__.py
palm/plugins/test_internal/test_internal_plugin.py
palm/plugins/test_internal/commands/__init__.py
palm/plugins/test_internal/commands/cmd_run.py
palm-2.6.0.dist-info/LICENSE
palm-2.6.0.dist-info/METADATA
palm-2.6.0.dist-info/WHEEL
palm-2.6.0.dist-info/entry_points.txt
palm-2.6.0.dist-info/top_level.txt
palm-2.6.0.dist-info/RECORD
