Metadata-Version: 2.1
Name: palm
Version: 2.6.0
Summary: Palm CLI
Home-page: https://github.com/palmetto/palm-cli
Author: Palmetto - Data & Analytics team
Author-email: data-analytics-team@palmetto.com
License: Apache License 2.0
Platform: UNKNOWN
Classifier: Development Status :: 4 - Beta
Classifier: License :: OSI Approved :: Apache Software License
License-File: LICENSE
Requires-Dist: click (<9.0,>=8.1)
Requires-Dist: cookiecutter (>=2.0)
Requires-Dist: deepmerge (>=1.0.0)
Requires-Dist: jinja2 (>=3.0)
Requires-Dist: pydantic (>=1.9)
Requires-Dist: pygit2 (>=1.5)
Requires-Dist: pyyaml (>=5.0)
